[
  {
    "vendor_key": "bakbattahl_vocation_guild",
    "name": "Bakbattahl Vocation Guild",
    "npc_key": null,
    "location_key": "bakbattahl_vocation_guild",
    "vendor_type": "vocation_guild",
    "currency_type": "discipline",
    "spoiler_level": 1,
    "notes": "Battahl vocation hub for later route changes.",
    "inventory": []
  },
  {
    "vendor_key": "dragonforged_vendor",
    "name": "Dragonforged",
    "npc_key": "dragonforged_npc",
    "location_key": "dragonforged",
    "vendor_type": "special_vendor",
    "currency_type": "wyrmslife_crystals",
    "spoiler_level": 2,
    "notes": "Late-game gear/vendor route placeholder.",
    "inventory": [
      {
        "item_key": "portcrystal",
        "name": "Portcrystal",
        "price_gold": 20,
        "stock_quantity": 1,
        "restocks": 0,
        "available_after_flag_key": "currency:wlc_20",
        "available_before_flag_key": null,
        "is_limited": 1,
        "sort_order": 10,
        "notes": "Costs 20 Wyrmslife Crystals at Dragonforged; WLC currency, not gold."
      }
    ]
  },
  {
    "vendor_key": "earland_bakbattahl",
    "name": "Earland",
    "npc_key": "earland",
    "location_key": "earland_bakbattahl_east_stall",
    "vendor_type": "special_merchant",
    "currency_type": "gold",
    "spoiler_level": 2,
    "notes": "Newt Liqueur source in East Bakbattahl; verify stock behavior.",
    "inventory": [
      {
        "item_key": "newt_liqueur",
        "name": "Newt Liqueur",
        "price_gold": 2000,
        "stock_quantity": 1,
        "restocks": 0,
        "available_after_flag_key": null,
        "available_before_flag_key": null,
        "is_limited": 1,
        "sort_order": 10,
        "notes": "Merchant source reported in east Bakbattahl; verify availability."
      },
      {
        "item_key": "newt_liqueur",
        "name": "Newt Liqueur",
        "price_gold": 2000,
        "stock_quantity": 1,
        "restocks": 0,
        "available_after_flag_key": null,
        "available_before_flag_key": null,
        "is_limited": 1,
        "sort_order": 10,
        "notes": "Merchant source reported in east Bakbattahl; verify availability."
      },
      {
        "item_key": "newt_liqueur",
        "name": "Newt Liqueur",
        "price_gold": 2000,
        "stock_quantity": 1,
        "restocks": 0,
        "available_after_flag_key": null,
        "available_before_flag_key": null,
        "is_limited": 1,
        "sort_order": 10,
        "notes": "Merchant source reported in east Bakbattahl; verify availability."
      }
    ]
  },
  {
    "vendor_key": "higgs_tavern_stand",
    "name": "Higg's Tavern Stand",
    "npc_key": null,
    "location_key": "higgs_tavern_stand",
    "vendor_type": "tavern_shop",
    "currency_type": "gold",
    "spoiler_level": 2,
    "notes": "Relevant later for Newt Liqueur/Warfarer planning.",
    "inventory": [
      {
        "item_key": "newt_liqueur",
        "name": "Newt Liqueur",
        "price_gold": 5000,
        "stock_quantity": 3,
        "restocks": 0,
        "available_after_flag_key": "access_unlocked:higgs_secret_shop",
        "available_before_flag_key": null,
        "is_limited": 1,
        "sort_order": 10,
        "notes": "Secret shop route; wear Beastren Mask and perform sack interaction; stock/availability should be verified."
      }
    ]
  },
  {
    "vendor_key": "ibrahims_scrap_store",
    "name": "Ibrahim's Scrap Store",
    "npc_key": "ibrahim",
    "location_key": "ibrahims_scrap_store",
    "vendor_type": "scrap_store",
    "currency_type": "gold",
    "spoiler_level": 1,
    "notes": "Beastren Mask source before Higg's Tavern Stand route.",
    "inventory": [
      {
        "item_key": "beastren_mask",
        "name": "Beastren Mask",
        "price_gold": 8700,
        "stock_quantity": 1,
        "restocks": 0,
        "available_after_flag_key": null,
        "available_before_flag_key": null,
        "is_limited": 0,
        "sort_order": 10,
        "notes": "Mask route for Higg's Tavern Stand."
      },
      {
        "item_key": "beastren_mask",
        "name": "Beastren Mask",
        "price_gold": 8700,
        "stock_quantity": 1,
        "restocks": 0,
        "available_after_flag_key": null,
        "available_before_flag_key": null,
        "is_limited": 0,
        "sort_order": 10,
        "notes": "Mask route for Higg's Tavern Stand."
      },
      {
        "item_key": "beastren_mask",
        "name": "Beastren Mask",
        "price_gold": 8700,
        "stock_quantity": 1,
        "restocks": 0,
        "available_after_flag_key": null,
        "available_before_flag_key": null,
        "is_limited": 0,
        "sort_order": 10,
        "notes": "Mask route for Higg's Tavern Stand."
      }
    ]
  },
  {
    "vendor_key": "rodericks_smithy",
    "name": "Roderick's Smithy",
    "npc_key": "roderick",
    "location_key": "rodericks_smithy",
    "vendor_type": "weapon_shop",
    "currency_type": "gold",
    "spoiler_level": 0,
    "notes": "Important shop/NPC for Vocation Frustration clue.",
    "inventory": []
  },
  {
    "vendor_key": "vernworth_vocation_guild",
    "name": "Vernworth Vocation Guild",
    "npc_key": "klaus",
    "location_key": "vernworth_vocation_guild",
    "vendor_type": "vocation_guild",
    "currency_type": "discipline",
    "spoiler_level": 1,
    "notes": "Use for vocation unlock/purchase context, not normal item inventory.",
    "inventory": []
  },
  {
    "vendor_key": "vernworth_weapon_shop",
    "name": "Vernworth Weapon Shop",
    "npc_key": null,
    "location_key": "vernworth",
    "vendor_type": "weapon_shop",
    "currency_type": "gold",
    "spoiler_level": 0,
    "notes": "Use actual shop NPC/name after verification.",
    "inventory": []
  },
  {
    "vendor_key": "volcanic_island_hot_springs",
    "name": "Volcanic Island Hot Springs",
    "npc_key": null,
    "location_key": "volcanic_island_hot_springs",
    "vendor_type": "service",
    "currency_type": "gold",
    "spoiler_level": 2,
    "notes": "Hot springs location for Lamond/Warfarer route context.",
    "inventory": []
  }
]